lossrider/__init__.py
lossrider/lossridersrc.py
lossrider-0.0.3.dist-info/LICENSE
lossrider-0.0.3.dist-info/METADATA
lossrider-0.0.3.dist-info/WHEEL
lossrider-0.0.3.dist-info/top_level.txt
lossrider-0.0.3.dist-info/RECORD
