Metadata-Version: 2.1
Name: lossrider
Version: 0.0.3
Summary: A plotting library that create Line Rider maps
Author-email: Josef Dean <email@josefdean.co.uk>
Project-URL: Homepage, https://github.com/jndean/LossRider
Classifier: Programming Language :: Python :: 3
Classifier: License :: OSI Approved :: MIT License
Classifier: Operating System :: OS Independent
Requires-Python: >=3.6
License-File: LICENSE
Requires-Dist: pandas
